Workbook

Sheet Synthèse
A1: Synthèse mensuelle
A2: Tout est calculé à partir des onglets Charges, Revenus et Comptes. Ne rien saisir ici.
A3: 1. Par personne
A4: Personne | B4: Salaires mensuels | C4: Participations aux comptes joints | D4: Charges payées directement (compte perso) | E4: Total charges supportées | F4: Taux d'effort | G4: Reste après charges communes | H4: Charges perso (détail ou forfait) | I4: Reste après charges perso | J4: Épargne perso | K4: Reste libre (loisirs…)
A5: =Paramètres!$B$4 -> Alex | B5: =SUMIFS(Revenus!$F$5:$F$24,Revenus!$B$5:$B$24,"Salaire",Revenus!$C$5:$C$24,A5) -> 2400 | C5: =SUM(E$13:E$22) -> 1424.2859 | D5: =IF(Paramètres!$B$6="",0,IFERROR(INDEX($C$13:$C$22,MATCH(Paramètres!$B$6,$A$13:$A$22,0)),0)) -> 0 | E5: =C5+D5 -> 1424.2859 | F5: =IF(B5=0,0,E5/B5) -> 0.59345244 | G5: =IF(Paramètres!$B$6="",0,IFERROR(INDEX($J$13:$J$22,MATCH(Paramètres!$B$6,$A$13:$A$22,0)),0)) -> 975.71414 | H5: =IF(Paramètres!B$15="Forfait",Paramètres!B$16,SUMIFS('Charges perso'!$F$5:$F$44,'Charges perso'!$B$5:$B$44,A5)) -> 86 | I5: =G5-H5 -> 889.71414 | J5: =MAX(0,IF(Paramètres!B$17="Pourcentage",Paramètres!B$18*MAX(0,I5),Paramètres!B$19)) -> 266.91424 | K5: =I5-J5 -> 622.7999
A6: =Paramètres!$B$5 -> Sam | B6: =SUMIFS(Revenus!$F$5:$F$24,Revenus!$B$5:$B$24,"Salaire",Revenus!$C$5:$C$24,A6) -> 1900 | C6: =SUM(F$13:F$22) -> 1219.7141 | D6: =IF(Paramètres!$B$7="",0,IFERROR(INDEX($C$13:$C$22,MATCH(Paramètres!$B$7,$A$13:$A$22,0)),0)) -> 28 | E6: =C6+D6 -> 1247.7141 | F6: =IF(B6=0,0,E6/B6) -> 0.65669165 | G6: =IF(Paramètres!$B$7="",0,IFERROR(INDEX($J$13:$J$22,MATCH(Paramètres!$B$7,$A$13:$A$22,0)),0)) -> 652.28586 | H6: =IF(Paramètres!C$15="Forfait",Paramètres!C$16,SUMIFS('Charges perso'!$F$5:$F$44,'Charges perso'!$B$5:$B$44,A6)) -> 350 | I6: =G6-H6 -> 302.28586 | J6: =MAX(0,IF(Paramètres!C$17="Pourcentage",Paramètres!C$18*MAX(0,I6),Paramètres!C$19)) -> 200 | K6: =I6-J6 -> 102.28586
A7: Total foyer | B7: =SUM(B5:B6) -> 4300 | C7: =SUM(C5:C6) -> 2644 | D7: =SUM(D5:D6) -> 28 | E7: =SUM(E5:E6) -> 2672 | F7: =IF(B7=0,0,E7/B7) -> 0.62139535 | G7: =SUM(G5:G6) -> 1628 | H7: =SUM(H5:H6) -> 436 | I7: =SUM(I5:I6) -> 1192 | J7: =SUM(J5:J6) -> 466.91424 | K7: =SUM(K5:K6) -> 725.08576
A9: 2. Par compte : ce que chacun doit virer chaque mois
A10: Un compte joint est alimenté par les virements des deux personnes (colonnes E et F) = charges du compte − aides reçues dessus, réparties selon la répartition de chaque charge.
A12: Compte | B12: Type | C12: Charges débitées / virements émis | D12: Aides & autres recettes reçues | E12: ="À virer par "&Paramètres!$B$4 -> À virer par Alex | F12: ="À virer par "&Paramètres!$B$5 -> À virer par Sam | G12: Salaires reçus | H12: Virements reçus (d'autres comptes) | I12: Participations versées (vers comptes joints) | J12: Solde mensuel prévisionnel
A13: =IF(Comptes!A5="","",Comptes!A5) -> Compte Alex | B13: =IF($A13="","",Comptes!B5) -> Personnel | C13: =IF($A13="","",SUMIFS(Charges!$F$5:$F$54,Charges!$H$5:$H$54,$A13)) -> 0 | D13: =IF($A13="","",SUMIFS(Revenus!$F$5:$F$24,Revenus!$G$5:$G$24,$A13,Revenus!$B$5:$B$24,"<>Salaire")) -> 0 | E13: =IF($A13="","",IF($B13="Joint",IF($C13=0,0,($C13-$D13)*SUMIFS(Charges!$M$5:$M$54,Charges!$H$5:$H$54,$A13)/$C13),0)) -> 0 | F13: =IF($A13="","",IF($B13="Joint",IF($C13=0,0,($C13-$D13)*SUMIFS(Charges!$N$5:$N$54,Charges!$H$5:$H$54,$A13)/$C13),0)) -> 0 | G13: =IF($A13="","",SUMIFS(Revenus!$F$5:$F$24,Revenus!$G$5:$G$24,$A13,Revenus!$B$5:$B$24,"Salaire")) -> 2400 | H13: =IF($A13="","",SUMIFS(Charges!$F$5:$F$54,Charges!$I$5:$I$54,$A13,Charges!$G$5:$G$54,"Virement")) -> 0 | I13: =IF($A13="","",IF($A13=Paramètres!$B$6,SUM($E$13:$E$22),IF($A13=Paramètres!$B$7,SUM($F$13:$F$22),0))) -> 1424.2859 | J13: =IF($A13="","",G13+D13+H13+IF(B13="Joint",E13+F13,0)-C13-I13) -> 975.71414
A14: =IF(Comptes!A6="","",Comptes!A6) -> Compte Sam | B14: =IF($A14="","",Comptes!B6) -> Personnel | C14: =IF($A14="","",SUMIFS(Charges!$F$5:$F$54,Charges!$H$5:$H$54,$A14)) -> 28 | D14: =IF($A14="","",SUMIFS(Revenus!$F$5:$F$24,Revenus!$G$5:$G$24,$A14,Revenus!$B$5:$B$24,"<>Salaire")) -> 0 | E14: =IF($A14="","",IF($B14="Joint",IF($C14=0,0,($C14-$D14)*SUMIFS(Charges!$M$5:$M$54,Charges!$H$5:$H$54,$A14)/$C14),0)) -> 0 | F14: =IF($A14="","",IF($B14="Joint",IF($C14=0,0,($C14-$D14)*SUMIFS(Charges!$N$5:$N$54,Charges!$H$5:$H$54,$A14)/$C14),0)) -> 0 | G14: =IF($A14="","",SUMIFS(Revenus!$F$5:$F$24,Revenus!$G$5:$G$24,$A14,Revenus!$B$5:$B$24,"Salaire")) -> 1900 | H14: =IF($A14="","",SUMIFS(Charges!$F$5:$F$54,Charges!$I$5:$I$54,$A14,Charges!$G$5:$G$54,"Virement")) -> 0 | I14: =IF($A14="","",IF($A14=Paramètres!$B$6,SUM($E$13:$E$22),IF($A14=Paramètres!$B$7,SUM($F$13:$F$22),0))) -> 1219.7141 | J14: =IF($A14="","",G14+D14+H14+IF(B14="Joint",E14+F14,0)-C14-I14) -> 652.28586
A15: =IF(Comptes!A7="","",Comptes!A7) -> Joint Logement | B15: =IF($A15="","",Comptes!B7) -> Joint | C15: =IF($A15="","",SUMIFS(Charges!$F$5:$F$54,Charges!$H$5:$H$54,$A15)) -> 1433.3333 | D15: =IF($A15="","",SUMIFS(Revenus!$F$5:$F$24,Revenus!$G$5:$G$24,$A15,Revenus!$B$5:$B$24,"<>Salaire")) -> 0 | E15: =IF($A15="","",IF($B15="Joint",IF($C15=0,0,($C15-$D15)*SUMIFS(Charges!$M$5:$M$54,Charges!$H$5:$H$54,$A15)/$C15),0)) -> 789.82558 | F15: =IF($A15="","",IF($B15="Joint",IF($C15=0,0,($C15-$D15)*SUMIFS(Charges!$N$5:$N$54,Charges!$H$5:$H$54,$A15)/$C15),0)) -> 643.50775 | G15: =IF($A15="","",SUMIFS(Revenus!$F$5:$F$24,Revenus!$G$5:$G$24,$A15,Revenus!$B$5:$B$24,"Salaire")) -> 0 | H15: =IF($A15="","",SUMIFS(Charges!$F$5:$F$54,Charges!$I$5:$I$54,$A15,Charges!$G$5:$G$54,"Virement")) -> 0 | I15: =IF($A15="","",IF($A15=Paramètres!$B$6,SUM($E$13:$E$22),IF($A15=Paramètres!$B$7,SUM($F$13:$F$22),0))) -> 0 | J15: =IF($A15="","",G15+D15+H15+IF(B15="Joint",E15+F15,0)-C15-I15) -> 0
A16: =IF(Comptes!A8="","",Comptes!A8) -> Joint Vie courante | B16: =IF($A16="","",Comptes!B8) -> Joint | C16: =IF($A16="","",SUMIFS(Charges!$F$5:$F$54,Charges!$H$5:$H$54,$A16)) -> 1370.6667 | D16: =IF($A16="","",SUMIFS(Revenus!$F$5:$F$24,Revenus!$G$5:$G$24,$A16,Revenus!$B$5:$B$24,"<>Salaire")) -> 230 | E16: =IF($A16="","",IF($B16="Joint",IF($C16=0,0,($C16-$D16)*SUMIFS(Charges!$M$5:$M$54,Charges!$H$5:$H$54,$A16)/$C16),0)) -> 599.46028 | F16: =IF($A16="","",IF($B16="Joint",IF($C16=0,0,($C16-$D16)*SUMIFS(Charges!$N$5:$N$54,Charges!$H$5:$H$54,$A16)/$C16),0)) -> 541.20639 | G16: =IF($A16="","",SUMIFS(Revenus!$F$5:$F$24,Revenus!$G$5:$G$24,$A16,Revenus!$B$5:$B$24,"Salaire")) -> 0 | H16: =IF($A16="","",SUMIFS(Charges!$F$5:$F$54,Charges!$I$5:$I$54,$A16,Charges!$G$5:$G$54,"Virement")) -> 0 | I16: =IF($A16="","",IF($A16=Paramètres!$B$6,SUM($E$13:$E$22),IF($A16=Paramètres!$B$7,SUM($F$13:$F$22),0))) -> 0 | J16: =IF($A16="","",G16+D16+H16+IF(B16="Joint",E16+F16,0)-C16-I16) -> 0
A17: =IF(Comptes!A9="","",Comptes!A9) -> Joint Abonnements | B17: =IF($A17="","",Comptes!B9) -> Joint | C17: =IF($A17="","",SUMIFS(Charges!$F$5:$F$54,Charges!$H$5:$H$54,$A17)) -> 70 | D17: =IF($A17="","",SUMIFS(Revenus!$F$5:$F$24,Revenus!$G$5:$G$24,$A17,Revenus!$B$5:$B$24,"<>Salaire")) -> 0 | E17: =IF($A17="","",IF($B17="Joint",IF($C17=0,0,($C17-$D17)*SUMIFS(Charges!$M$5:$M$54,Charges!$H$5:$H$54,$A17)/$C17),0)) -> 35 | F17: =IF($A17="","",IF($B17="Joint",IF($C17=0,0,($C17-$D17)*SUMIFS(Charges!$N$5:$N$54,Charges!$H$5:$H$54,$A17)/$C17),0)) -> 35 | G17: =IF($A17="","",SUMIFS(Revenus!$F$5:$F$24,Revenus!$G$5:$G$24,$A17,Revenus!$B$5:$B$24,"Salaire")) -> 0 | H17: =IF($A17="","",SUMIFS(Charges!$F$5:$F$54,Charges!$I$5:$I$54,$A17,Charges!$G$5:$G$54,"Virement")) -> 0 | I17: =IF($A17="","",IF($A17=Paramètres!$B$6,SUM($E$13:$E$22),IF($A17=Paramètres!$B$7,SUM($F$13:$F$22),0))) -> 0 | J17: =IF($A17="","",G17+D17+H17+IF(B17="Joint",E17+F17,0)-C17-I17) -> 0
A18: =IF(Comptes!A10="","",Comptes!A10) -> Livret A | B18: =IF($A18="","",Comptes!B10) -> Épargne | C18: =IF($A18="","",SUMIFS(Charges!$F$5:$F$54,Charges!$H$5:$H$54,$A18)) -> 0 | D18: =IF($A18="","",SUMIFS(Revenus!$F$5:$F$24,Revenus!$G$5:$G$24,$A18,Revenus!$B$5:$B$24,"<>Salaire")) -> 0 | E18: =IF($A18="","",IF($B18="Joint",IF($C18=0,0,($C18-$D18)*SUMIFS(Charges!$M$5:$M$54,Charges!$H$5:$H$54,$A18)/$C18),0)) -> 0 | F18: =IF($A18="","",IF($B18="Joint",IF($C18=0,0,($C18-$D18)*SUMIFS(Charges!$N$5:$N$54,Charges!$H$5:$H$54,$A18)/$C18),0)) -> 0 | G18: =IF($A18="","",SUMIFS(Revenus!$F$5:$F$24,Revenus!$G$5:$G$24,$A18,Revenus!$B$5:$B$24,"Salaire")) -> 0 | H18: =IF($A18="","",SUMIFS(Charges!$F$5:$F$54,Charges!$I$5:$I$54,$A18,Charges!$G$5:$G$54,"Virement")) -> 150 | I18: =IF($A18="","",IF($A18=Paramètres!$B$6,SUM($E$13:$E$22),IF($A18=Paramètres!$B$7,SUM($F$13:$F$22),0))) -> 0 | J18: =IF($A18="","",G18+D18+H18+IF(B18="Joint",E18+F18,0)-C18-I18) -> 150
A19: =IF(Comptes!A11="","",Comptes!A11) -> Livret imprévus | B19: =IF($A19="","",Comptes!B11) -> Épargne | C19: =IF($A19="","",SUMIFS(Charges!$F$5:$F$54,Charges!$H$5:$H$54,$A19)) -> 0 | D19: =IF($A19="","",SUMIFS(Revenus!$F$5:$F$24,Revenus!$G$5:$G$24,$A19,Revenus!$B$5:$B$24,"<>Salaire")) -> 0 | E19: =IF($A19="","",IF($B19="Joint",IF($C19=0,0,($C19-$D19)*SUMIFS(Charges!$M$5:$M$54,Charges!$H$5:$H$54,$A19)/$C19),0)) -> 0 | F19: =IF($A19="","",IF($B19="Joint",IF($C19=0,0,($C19-$D19)*SUMIFS(Charges!$N$5:$N$54,Charges!$H$5:$H$54,$A19)/$C19),0)) -> 0 | G19: =IF($A19="","",SUMIFS(Revenus!$F$5:$F$24,Revenus!$G$5:$G$24,$A19,Revenus!$B$5:$B$24,"Salaire")) -> 0 | H19: =IF($A19="","",SUMIFS(Charges!$F$5:$F$54,Charges!$I$5:$I$54,$A19,Charges!$G$5:$G$54,"Virement")) -> 129 | I19: =IF($A19="","",IF($A19=Paramètres!$B$6,SUM($E$13:$E$22),IF($A19=Paramètres!$B$7,SUM($F$13:$F$22),0))) -> 0 | J19: =IF($A19="","",G19+D19+H19+IF(B19="Joint",E19+F19,0)-C19-I19) -> 129
A20: =IF(Comptes!A12="","",Comptes!A12) | B20: =IF($A20="","",Comptes!B12) | C20: =IF($A20="","",SUMIFS(Charges!$F$5:$F$54,Charges!$H$5:$H$54,$A20)) | D20: =IF($A20="","",SUMIFS(Revenus!$F$5:$F$24,Revenus!$G$5:$G$24,$A20,Revenus!$B$5:$B$24,"<>Salaire")) | E20: =IF($A20="","",IF($B20="Joint",IF($C20=0,0,($C20-$D20)*SUMIFS(Charges!$M$5:$M$54,Charges!$H$5:$H$54,$A20)/$C20),0)) | F20: =IF($A20="","",IF($B20="Joint",IF($C20=0,0,($C20-$D20)*SUMIFS(Charges!$N$5:$N$54,Charges!$H$5:$H$54,$A20)/$C20),0)) | G20: =IF($A20="","",SUMIFS(Revenus!$F$5:$F$24,Revenus!$G$5:$G$24,$A20,Revenus!$B$5:$B$24,"Salaire")) | H20: =IF($A20="","",SUMIFS(Charges!$F$5:$F$54,Charges!$I$5:$I$54,$A20,Charges!$G$5:$G$54,"Virement")) | I20: =IF($A20="","",IF($A20=Paramètres!$B$6,SUM($E$13:$E$22),IF($A20=Paramètres!$B$7,SUM($F$13:$F$22),0))) | J20: =IF($A20="","",G20+D20+H20+IF(B20="Joint",E20+F20,0)-C20-I20)
A21: =IF(Comptes!A13="","",Comptes!A13) | B21: =IF($A21="","",Comptes!B13) | C21: =IF($A21="","",SUMIFS(Charges!$F$5:$F$54,Charges!$H$5:$H$54,$A21)) | D21: =IF($A21="","",SUMIFS(Revenus!$F$5:$F$24,Revenus!$G$5:$G$24,$A21,Revenus!$B$5:$B$24,"<>Salaire")) | E21: =IF($A21="","",IF($B21="Joint",IF($C21=0,0,($C21-$D21)*SUMIFS(Charges!$M$5:$M$54,Charges!$H$5:$H$54,$A21)/$C21),0)) | F21: =IF($A21="","",IF($B21="Joint",IF($C21=0,0,($C21-$D21)*SUMIFS(Charges!$N$5:$N$54,Charges!$H$5:$H$54,$A21)/$C21),0)) | G21: =IF($A21="","",SUMIFS(Revenus!$F$5:$F$24,Revenus!$G$5:$G$24,$A21,Revenus!$B$5:$B$24,"Salaire")) | H21: =IF($A21="","",SUMIFS(Charges!$F$5:$F$54,Charges!$I$5:$I$54,$A21,Charges!$G$5:$G$54,"Virement")) | I21: =IF($A21="","",IF($A21=Paramètres!$B$6,SUM($E$13:$E$22),IF($A21=Paramètres!$B$7,SUM($F$13:$F$22),0))) | J21: =IF($A21="","",G21+D21+H21+IF(B21="Joint",E21+F21,0)-C21-I21)
A22: =IF(Comptes!A14="","",Comptes!A14) | B22: =IF($A22="","",Comptes!B14) | C22: =IF($A22="","",SUMIFS(Charges!$F$5:$F$54,Charges!$H$5:$H$54,$A22)) | D22: =IF($A22="","",SUMIFS(Revenus!$F$5:$F$24,Revenus!$G$5:$G$24,$A22,Revenus!$B$5:$B$24,"<>Salaire")) | E22: =IF($A22="","",IF($B22="Joint",IF($C22=0,0,($C22-$D22)*SUMIFS(Charges!$M$5:$M$54,Charges!$H$5:$H$54,$A22)/$C22),0)) | F22: =IF($A22="","",IF($B22="Joint",IF($C22=0,0,($C22-$D22)*SUMIFS(Charges!$N$5:$N$54,Charges!$H$5:$H$54,$A22)/$C22),0)) | G22: =IF($A22="","",SUMIFS(Revenus!$F$5:$F$24,Revenus!$G$5:$G$24,$A22,Revenus!$B$5:$B$24,"Salaire")) | H22: =IF($A22="","",SUMIFS(Charges!$F$5:$F$54,Charges!$I$5:$I$54,$A22,Charges!$G$5:$G$54,"Virement")) | I22: =IF($A22="","",IF($A22=Paramètres!$B$6,SUM($E$13:$E$22),IF($A22=Paramètres!$B$7,SUM($F$13:$F$22),0))) | J22: =IF($A22="","",G22+D22+H22+IF(B22="Joint",E22+F22,0)-C22-I22)
A23: Total | C23: =SUM(C13:C22) -> 2902 | D23: =SUM(D13:D22) -> 230 | E23: =SUM(E13:E22) -> 1424.2859 | F23: =SUM(F13:F22) -> 1219.7141 | G23: =SUM(G13:G22) -> 4300 | H23: =SUM(H13:H22) -> 279 | I23: =SUM(I13:I22) -> 2644 | J23: =SUM(J13:J22) -> 1907
A25: Lecture : un compte joint à solde 0 est équilibré. Un compte perso à solde positif = reste à vivre ; négatif = salaire insuffisant. Les aides sont réparties sur les deux personnes au prorata de leurs parts de charges (hypothèse).
A27: 3. Charges communes : fixe vs variable (mensuel)
A28: Fixe | B28: =SUMIFS(Charges!$F$5:$F$54,Charges!$C$5:$C$54,"Fixe") -> 1731.3333 | C28: =IF($B$30=0,0,B28/$B$30) -> 0.59660005
A29: Variable / estimé | B29: =SUMIFS(Charges!$F$5:$F$54,Charges!$C$5:$C$54,"Variable") -> 1170.6667 | C29: =IF($B$30=0,0,B29/$B$30) -> 0.40339995
A30: Total | B30: =B28+B29 -> 2902 | C30: =C28+C29 -> 1

Sheet Paramètres
A1: Paramètres du foyer
A2: Cellules jaunes à police bleue = à modifier. Tout le reste se calcule.
D3: Périodicité | E3: Nb de mois
A4: Personne 1 | B4: Alex | D4: Mensuelle | E4: 1
A5: Personne 2 | B5: Sam | D5: Trimestrielle | E5: 3
A6: Compte perso de la Personne 1 | B6: Compte Alex | D6: Semestrielle | E6: 6
A7: Compte perso de la Personne 2 | B7: Compte Sam | D7: Annuelle | E7: 12
A9: Part de la Personne 1 dans les salaires (pour « Prorata salaires ») | B9: =IFERROR(SUMIFS(Revenus!$F$5:$F$24,Revenus!$B$5:$B$24,"Salaire",Revenus!$C$5:$C$24,$B$4)/SUMIFS(Revenus!$F$5:$F$24,Revenus!$B$5:$B$24,"Salaire"),0.5) -> 0.55813953
A10: Hypothèse : 50 % si aucun salaire n'est saisi.
A12: Modes de répartition possibles : 50/50 · Prorata salaires · Personne 1 seul · Personne 2 seul
A14: Budget personnel (le « reste libre ») | B14: =$B$4 -> Alex | C14: =$B$5 -> Sam
A15: Charges perso : mode (Détail = onglet « Charges perso » ; Forfait = somme arbitraire) | B15: Détail | C15: Forfait
A16: Forfait charges perso (€/mois), utilisé si mode Forfait | B16: 0 | C16: 350
A17: Épargne perso : mode (Pourcentage ou Montant) | B17: Pourcentage | C17: Montant
A18: Épargne perso : pourcentage du reste (si Pourcentage) | B18: 0.3 | C18: 0
A19: Épargne perso : montant €/mois (si Montant) | B19: 0 | C19: 200
A20: Si l'un de vous ne veut pas détailler ses comptes : mode Forfait + une somme. Ses lignes éventuelles dans « Charges perso » sont alors ignorées.
A22: Provision imprévus (% des salaires du foyer) | B22: 0.03
A23: Alimente la ligne « Provision imprévus » de l'onglet Charges (réparties 50/50, sur le compte joint indiqué).

Sheet Comptes
A1: Comptes bancaires
A2: Paramétrez ici vos comptes (10 lignes). Le nom saisi ici alimente les listes déroulantes des autres onglets.
A4: Nom du compte | B4: Type | C4: Titulaire(s) | D4: Usage
A5: Compte Alex | B5: Personnel | C5: Alex | D5: Salaire d'Alex, dépenses perso
A6: Compte Sam | B6: Personnel | C6: Sam | D6: Salaire de Sam, dépenses perso
A7: Joint Logement | B7: Joint | C7: Alex & Sam | D7: Emprunt, assurances, énergie, taxe foncière
A8: Joint Vie courante | B8: Joint | C8: Alex & Sam | D8: Courses, voiture, enfants, aides CAF
A9: Joint Abonnements | B9: Joint | C9: Alex & Sam | D9: Internet, streaming, etc.
A10: Livret A | B10: Épargne | C10: Alex & Sam | D10: Épargne (reçoit des virements)
A11: Livret imprévus | B11: Épargne | C11: Alex & Sam | D11: Provision pour les dépenses imprévues

Sheet Charges
A1: Charges (dépenses récurrentes)
A2: Remplir les colonnes jaunes (50 lignes). Montant = montant par période ; le mensuel et les parts se calculent. Virement : indiquer le compte destinataire (liste libre). Dépenses irrégulières : saisir une enveloppe annuelle, elle est lissée par mois.
A4: Libellé | B4: Catégorie | C4: Nature | D4: Périodicité | E4: Montant (€ par période) | F4: Montant mensuel | G4: Mode de paiement | H4: Compte débité | I4: Compte destinataire (si virement) | J4: Jour du mois | K4: Répartition | L4: Part P1 (%) | M4: ="Part "&Paramètres!$B$4&" (€/mois)" -> Part Alex (€/mois) | N4: ="Part "&Paramètres!$B$5&" (€/mois)" -> Part Sam (€/mois)
A5: Emprunt immobilier | B5: Logement | C5: Fixe | D5: Mensuelle | E5: 1150 | F5: =IF(A5="","",IFERROR(E5/INDEX(Paramètres!$E$4:$E$7,MATCH(D5,Paramètres!$D$4:$D$7,0)),0)) -> 1150 | G5: Prélèvement | H5: Joint Logement | J5: 5 | K5: Prorata salaires | L5: =IF(A5="","",IF(K5="50/50",0.5,IF(K5="Prorata salaires",Paramètres!$B$9,IF(K5="Personne 1 seul",1,IF(K5="Personne 2 seul",0,0.5))))) -> 0.55813953 | M5: =IF(A5="","",F5*L5) -> 641.86047 | N5: =IF(A5="","",F5-M5) -> 508.13953
A6: Assurance emprunt | B6: Logement | C6: Fixe | D6: Mensuelle | E6: 45 | F6: =IF(A6="","",IFERROR(E6/INDEX(Paramètres!$E$4:$E$7,MATCH(D6,Paramètres!$D$4:$D$7,0)),0)) -> 45 | G6: Prélèvement | H6: Joint Logement | J6: 5 | K6: 50/50 | L6: =IF(A6="","",IF(K6="50/50",0.5,IF(K6="Prorata salaires",Paramètres!$B$9,IF(K6="Personne 1 seul",1,IF(K6="Personne 2 seul",0,0.5))))) -> 0.5 | M6: =IF(A6="","",F6*L6) -> 22.5 | N6: =IF(A6="","",F6-M6) -> 22.5
A7: Taxe foncière | B7: Logement | C7: Fixe | D7: Annuelle | E7: 1300 | F7: =IF(A7="","",IFERROR(E7/INDEX(Paramètres!$E$4:$E$7,MATCH(D7,Paramètres!$D$4:$D$7,0)),0)) -> 108.33333 | G7: Prélèvement | H7: Joint Logement | J7: 15 | K7: Prorata salaires | L7: =IF(A7="","",IF(K7="50/50",0.5,IF(K7="Prorata salaires",Paramètres!$B$9,IF(K7="Personne 1 seul",1,IF(K7="Personne 2 seul",0,0.5))))) -> 0.55813953 | M7: =IF(A7="","",F7*L7) -> 60.465116 | N7: =IF(A7="","",F7-M7) -> 47.868217
A8: Électricité maison | B8: Énergie | C8: Variable | D8: Mensuelle | E8: 130 | F8: =IF(A8="","",IFERROR(E8/INDEX(Paramètres!$E$4:$E$7,MATCH(D8,Paramètres!$D$4:$D$7,0)),0)) -> 130 | G8: Prélèvement | H8: Joint Logement | J8: 12 | K8: 50/50 | L8: =IF(A8="","",IF(K8="50/50",0.5,IF(K8="Prorata salaires",Paramètres!$B$9,IF(K8="Personne 1 seul",1,IF(K8="Personne 2 seul",0,0.5))))) -> 0.5 | M8: =IF(A8="","",F8*L8) -> 65 | N8: =IF(A8="","",F8-M8) -> 65
A9: Électricité garage / local | B9: Énergie | C9: Variable | D9: Mensuelle | E9: 40 | F9: =IF(A9="","",IFERROR(E9/INDEX(Paramètres!$E$4:$E$7,MATCH(D9,Paramètres!$D$4:$D$7,0)),0)) -> 40 | G9: Prélèvement | H9: Joint Abonnements | J9: 14 | K9: 50/50 | L9: =IF(A9="","",IF(K9="50/50",0.5,IF(K9="Prorata salaires",Paramètres!$B$9,IF(K9="Personne 1 seul",1,IF(K9="Personne 2 seul",0,0.5))))) -> 0.5 | M9: =IF(A9="","",F9*L9) -> 20 | N9: =IF(A9="","",F9-M9) -> 20
A10: Internet / box | B10: Abonnements | C10: Fixe | D10: Mensuelle | E10: 30 | F10: =IF(A10="","",IFERROR(E10/INDEX(Paramètres!$E$4:$E$7,MATCH(D10,Paramètres!$D$4:$D$7,0)),0)) -> 30 | G10: Prélèvement | H10: Joint Abonnements | J10: 10 | K10: 50/50 | L10: =IF(A10="","",IF(K10="50/50",0.5,IF(K10="Prorata salaires",Paramètres!$B$9,IF(K10="Personne 1 seul",1,IF(K10="Personne 2 seul",0,0.5))))) -> 0.5 | M10: =IF(A10="","",F10*L10) -> 15 | N10: =IF(A10="","",F10-M10) -> 15
A11: Assurance auto (voiture d'Alex) | B11: Transport | C11: Fixe | D11: Trimestrielle | E11: 210 | F11: =IF(A11="","",IFERROR(E11/INDEX(Paramètres!$E$4:$E$7,MATCH(D11,Paramètres!$D$4:$D$7,0)),0)) -> 70 | G11: Prélèvement | H11: Joint Vie courante | J11: 1 | K11: Personne 1 seul | L11: =IF(A11="","",IF(K11="50/50",0.5,IF(K11="Prorata salaires",Paramètres!$B$9,IF(K11="Personne 1 seul",1,IF(K11="Personne 2 seul",0,0.5))))) -> 1 | M11: =IF(A11="","",F11*L11) -> 70 | N11: =IF(A11="","",F11-M11) -> 0
A12: Forfait mobile de Sam | B12: Abonnements | C12: Fixe | D12: Mensuelle | E12: 28 | F12: =IF(A12="","",IFERROR(E12/INDEX(Paramètres!$E$4:$E$7,MATCH(D12,Paramètres!$D$4:$D$7,0)),0)) -> 28 | G12: Prélèvement | H12: Compte Sam | J12: 8 | K12: Personne 2 seul | L12: =IF(A12="","",IF(K12="50/50",0.5,IF(K12="Prorata salaires",Paramètres!$B$9,IF(K12="Personne 1 seul",1,IF(K12="Personne 2 seul",0,0.5))))) -> 0 | M12: =IF(A12="","",F12*L12) -> 0 | N12: =IF(A12="","",F12-M12) -> 28
A13: Courses alimentaires | B13: Vie courante | C13: Variable | D13: Mensuelle | E13: 600 | F13: =IF(A13="","",IFERROR(E13/INDEX(Paramètres!$E$4:$E$7,MATCH(D13,Paramètres!$D$4:$D$7,0)),0)) -> 600 | G13: Carte | H13: Joint Vie courante | K13: 50/50 | L13: =IF(A13="","",IF(K13="50/50",0.5,IF(K13="Prorata salaires",Paramètres!$B$9,IF(K13="Personne 1 seul",1,IF(K13="Personne 2 seul",0,0.5))))) -> 0.5 | M13: =IF(A13="","",F13*L13) -> 300 | N13: =IF(A13="","",F13-M13) -> 300
A14: Épargne mensuelle | B14: Épargne | C14: Fixe | D14: Mensuelle | E14: 150 | F14: =IF(A14="","",IFERROR(E14/INDEX(Paramètres!$E$4:$E$7,MATCH(D14,Paramètres!$D$4:$D$7,0)),0)) -> 150 | G14: Virement | H14: Joint Vie courante | I14: Livret A | J14: 3 | K14: 50/50 | L14: =IF(A14="","",IF(K14="50/50",0.5,IF(K14="Prorata salaires",Paramètres!$B$9,IF(K14="Personne 1 seul",1,IF(K14="Personne 2 seul",0,0.5))))) -> 0.5 | M14: =IF(A14="","",F14*L14) -> 75 | N14: =IF(A14="","",F14-M14) -> 75
A15: Cantine des enfants | B15: Enfants | C15: Variable | D15: Mensuelle | E15: 90 | F15: =IF(A15="","",IFERROR(E15/INDEX(Paramètres!$E$4:$E$7,MATCH(D15,Paramètres!$D$4:$D$7,0)),0)) -> 90 | G15: Virement | H15: Joint Vie courante | I15: Mairie (cantine) | J15: 28 | K15: 50/50 | L15: =IF(A15="","",IF(K15="50/50",0.5,IF(K15="Prorata salaires",Paramètres!$B$9,IF(K15="Personne 1 seul",1,IF(K15="Personne 2 seul",0,0.5))))) -> 0.5 | M15: =IF(A15="","",F15*L15) -> 45 | N15: =IF(A15="","",F15-M15) -> 45
A16: Vêtements enfants (enveloppe lissée) | B16: Enfants | C16: Variable | D16: Annuelle | E16: 600 | F16: =IF(A16="","",IFERROR(E16/INDEX(Paramètres!$E$4:$E$7,MATCH(D16,Paramètres!$D$4:$D$7,0)),0)) -> 50 | G16: Carte | H16: Joint Vie courante | K16: 50/50 | L16: =IF(A16="","",IF(K16="50/50",0.5,IF(K16="Prorata salaires",Paramètres!$B$9,IF(K16="Personne 1 seul",1,IF(K16="Personne 2 seul",0,0.5))))) -> 0.5 | M16: =IF(A16="","",F16*L16) -> 25 | N16: =IF(A16="","",F16-M16) -> 25
A17: Médecin / pharmacie (provision) | B17: Santé | C17: Variable | D17: Mensuelle | E17: 30 | F17: =IF(A17="","",IFERROR(E17/INDEX(Paramètres!$E$4:$E$7,MATCH(D17,Paramètres!$D$4:$D$7,0)),0)) -> 30 | G17: Chèque | H17: Joint Vie courante | K17: 50/50 | L17: =IF(A17="","",IF(K17="50/50",0.5,IF(K17="Prorata salaires",Paramètres!$B$9,IF(K17="Personne 1 seul",1,IF(K17="Personne 2 seul",0,0.5))))) -> 0.5 | M17: =IF(A17="","",F17*L17) -> 15 | N17: =IF(A17="","",F17-M17) -> 15
A18: Cadeaux & fêtes (enveloppe lissée) | B18: Loisirs | C18: Variable | D18: Annuelle | E18: 500 | F18: =IF(A18="","",IFERROR(E18/INDEX(Paramètres!$E$4:$E$7,MATCH(D18,Paramètres!$D$4:$D$7,0)),0)) -> 41.666667 | G18: Carte | H18: Joint Vie courante | K18: 50/50 | L18: =IF(A18="","",IF(K18="50/50",0.5,IF(K18="Prorata salaires",Paramètres!$B$9,IF(K18="Personne 1 seul",1,IF(K18="Personne 2 seul",0,0.5))))) -> 0.5 | M18: =IF(A18="","",F18*L18) -> 20.833333 | N18: =IF(A18="","",F18-M18) -> 20.833333
A19: Provision imprévus (% des salaires) | B19: Imprévus | C19: Variable | D19: Mensuelle | E19: =Paramètres!$B$22*SUMIFS(Revenus!$F$5:$F$24,Revenus!$B$5:$B$24,"Salaire") -> 129 | F19: =IF(A19="","",IFERROR(E19/INDEX(Paramètres!$E$4:$E$7,MATCH(D19,Paramètres!$D$4:$D$7,0)),0)) -> 129 | G19: Virement | H19: Joint Vie courante | I19: Livret imprévus | J19: 3 | K19: 50/50 | L19: =IF(A19="","",IF(K19="50/50",0.5,IF(K19="Prorata salaires",Paramètres!$B$9,IF(K19="Personne 1 seul",1,IF(K19="Personne 2 seul",0,0.5))))) -> 0.5 | M19: =IF(A19="","",F19*L19) -> 64.5 | N19: =IF(A19="","",F19-M19) -> 64.5
A20: Aide à domicile (retrait espèces) | B20: Services | C20: Fixe | D20: Mensuelle | E20: 120 | F20: =IF(A20="","",IFERROR(E20/INDEX(Paramètres!$E$4:$E$7,MATCH(D20,Paramètres!$D$4:$D$7,0)),0)) -> 120 | G20: Espèces | H20: Joint Vie courante | J20: 1 | K20: 50/50 | L20: =IF(A20="","",IF(K20="50/50",0.5,IF(K20="Prorata salaires",Paramètres!$B$9,IF(K20="Personne 1 seul",1,IF(K20="Personne 2 seul",0,0.5))))) -> 0.5 | M20: =IF(A20="","",F20*L20) -> 60 | N20: =IF(A20="","",F20-M20) -> 60
A21: Argent de poche enfants (retrait espèces) | B21: Enfants | C21: Fixe | D21: Mensuelle | E21: 30 | F21: =IF(A21="","",IFERROR(E21/INDEX(Paramètres!$E$4:$E$7,MATCH(D21,Paramètres!$D$4:$D$7,0)),0)) -> 30 | G21: Espèces | H21: Joint Vie courante | J21: 1 | K21: 50/50 | L21: =IF(A21="","",IF(K21="50/50",0.5,IF(K21="Prorata salaires",Paramètres!$B$9,IF(K21="Personne 1 seul",1,IF(K21="Personne 2 seul",0,0.5))))) -> 0.5 | M21: =IF(A21="","",F21*L21) -> 15 | N21: =IF(A21="","",F21-M21) -> 15
A22: Marché & petits commerces (retrait espèces) | B22: Vie courante | C22: Variable | D22: Mensuelle | E22: 60 | F22: =IF(A22="","",IFERROR(E22/INDEX(Paramètres!$E$4:$E$7,MATCH(D22,Paramètres!$D$4:$D$7,0)),0)) -> 60 | G22: Espèces | H22: Joint Vie courante | K22: 50/50 | L22: =IF(A22="","",IF(K22="50/50",0.5,IF(K22="Prorata salaires",Paramètres!$B$9,IF(K22="Personne 1 seul",1,IF(K22="Personne 2 seul",0,0.5))))) -> 0.5 | M22: =IF(A22="","",F22*L22) -> 30 | N22: =IF(A22="","",F22-M22) -> 30
F23: =IF(A23="","",IFERROR(E23/INDEX(Paramètres!$E$4:$E$7,MATCH(D23,Paramètres!$D$4:$D$7,0)),0)) | L23: =IF(A23="","",IF(K23="50/50",0.5,IF(K23="Prorata salaires",Paramètres!$B$9,IF(K23="Personne 1 seul",1,IF(K23="Personne 2 seul",0,0.5))))) | M23: =IF(A23="","",F23*L23) | N23: =IF(A23="","",F23-M23)
F24: =IF(A24="","",IFERROR(E24/INDEX(Paramètres!$E$4:$E$7,MATCH(D24,Paramètres!$D$4:$D$7,0)),0)) | L24: =IF(A24="","",IF(K24="50/50",0.5,IF(K24="Prorata salaires",Paramètres!$B$9,IF(K24="Personne 1 seul",1,IF(K24="Personne 2 seul",0,0.5))))) | M24: =IF(A24="","",F24*L24) | N24: =IF(A24="","",F24-M24)
F25: =IF(A25="","",IFERROR(E25/INDEX(Paramètres!$E$4:$E$7,MATCH(D25,Paramètres!$D$4:$D$7,0)),0)) | L25: =IF(A25="","",IF(K25="50/50",0.5,IF(K25="Prorata salaires",Paramètres!$B$9,IF(K25="Personne 1 seul",1,IF(K25="Personne 2 seul",0,0.5))))) | M25: =IF(A25="","",F25*L25) | N25: =IF(A25="","",F25-M25)
F26: =IF(A26="","",IFERROR(E26/INDEX(Paramètres!$E$4:$E$7,MATCH(D26,Paramètres!$D$4:$D$7,0)),0)) | L26: =IF(A26="","",IF(K26="50/50",0.5,IF(K26="Prorata salaires",Paramètres!$B$9,IF(K26="Personne 1 seul",1,IF(K26="Personne 2 seul",0,0.5))))) | M26: =IF(A26="","",F26*L26) | N26: =IF(A26="","",F26-M26)
F27: =IF(A27="","",IFERROR(E27/INDEX(Paramètres!$E$4:$E$7,MATCH(D27,Paramètres!$D$4:$D$7,0)),0)) | L27: =IF(A27="","",IF(K27="50/50",0.5,IF(K27="Prorata salaires",Paramètres!$B$9,IF(K27="Personne 1 seul",1,IF(K27="Personne 2 seul",0,0.5))))) | M27: =IF(A27="","",F27*L27) | N27: =IF(A27="","",F27-M27)
F28: =IF(A28="","",IFERROR(E28/INDEX(Paramètres!$E$4:$E$7,MATCH(D28,Paramètres!$D$4:$D$7,0)),0)) | L28: =IF(A28="","",IF(K28="50/50",0.5,IF(K28="Prorata salaires",Paramètres!$B$9,IF(K28="Personne 1 seul",1,IF(K28="Personne 2 seul",0,0.5))))) | M28: =IF(A28="","",F28*L28) | N28: =IF(A28="","",F28-M28)
F29: =IF(A29="","",IFERROR(E29/INDEX(Paramètres!$E$4:$E$7,MATCH(D29,Paramètres!$D$4:$D$7,0)),0)) | L29: =IF(A29="","",IF(K29="50/50",0.5,IF(K29="Prorata salaires",Paramètres!$B$9,IF(K29="Personne 1 seul",1,IF(K29="Personne 2 seul",0,0.5))))) | M29: =IF(A29="","",F29*L29) | N29: =IF(A29="","",F29-M29)
F30: =IF(A30="","",IFERROR(E30/INDEX(Paramètres!$E$4:$E$7,MATCH(D30,Paramètres!$D$4:$D$7,0)),0)) | L30: =IF(A30="","",IF(K30="50/50",0.5,IF(K30="Prorata salaires",Paramètres!$B$9,IF(K30="Personne 1 seul",1,IF(K30="Personne 2 seul",0,0.5))))) | M30: =IF(A30="","",F30*L30) | N30: =IF(A30="","",F30-M30)
F31: =IF(A31="","",IFERROR(E31/INDEX(Paramètres!$E$4:$E$7,MATCH(D31,Paramètres!$D$4:$D$7,0)),0)) | L31: =IF(A31="","",IF(K31="50/50",0.5,IF(K31="Prorata salaires",Paramètres!$B$9,IF(K31="Personne 1 seul",1,IF(K31="Personne 2 seul",0,0.5))))) | M31: =IF(A31="","",F31*L31) | N31: =IF(A31="","",F31-M31)
F32: =IF(A32="","",IFERROR(E32/INDEX(Paramètres!$E$4:$E$7,MATCH(D32,Paramètres!$D$4:$D$7,0)),0)) | L32: =IF(A32="","",IF(K32="50/50",0.5,IF(K32="Prorata salaires",Paramètres!$B$9,IF(K32="Personne 1 seul",1,IF(K32="Personne 2 seul",0,0.5))))) | M32: =IF(A32="","",F32*L32) | N32: =IF(A32="","",F32-M32)
F33: =IF(A33="","",IFERROR(E33/INDEX(Paramètres!$E$4:$E$7,MATCH(D33,Paramètres!$D$4:$D$7,0)),0)) | L33: =IF(A33="","",IF(K33="50/50",0.5,IF(K33="Prorata salaires",Paramètres!$B$9,IF(K33="Personne 1 seul",1,IF(K33="Personne 2 seul",0,0.5))))) | M33: =IF(A33="","",F33*L33) | N33: =IF(A33="","",F33-M33)
F34: =IF(A34="","",IFERROR(E34/INDEX(Paramètres!$E$4:$E$7,MATCH(D34,Paramètres!$D$4:$D$7,0)),0)) | L34: =IF(A34="","",IF(K34="50/50",0.5,IF(K34="Prorata salaires",Paramètres!$B$9,IF(K34="Personne 1 seul",1,IF(K34="Personne 2 seul",0,0.5))))) | M34: =IF(A34="","",F34*L34) | N34: =IF(A34="","",F34-M34)
... F54: =IF(A54="","",IFERROR(E54/INDEX(Paramètres!$E$4:$E$7,MATCH(D54,Paramètres!$D$4:$D$7,0)),0)) | L54: =IF(A54="","",IF(K54="50/50",0.5,IF(K54="Prorata salaires",Paramètres!$B$9,IF(K54="Personne 1 seul",1,IF(K54="Personne 2 seul",0,0.5))))) | M54: =IF(A54="","",F54*L54) | N54: =IF(A54="","",F54-M54)
A55: TOTAL mensuel | F55: =SUM(F5:F54) -> 2902 | M55: =SUM(M5:M54) -> 1545.1589 | N55: =SUM(N5:N54) -> 1356.8411

Sheet Revenus
A1: Revenus et aides
A2: Salaires (arrivent sur le compte de chacun) et aides type CAF (peuvent arriver sur un compte joint). 20 lignes.
A4: Libellé | B4: Type | C4: Personne | D4: Montant (€ par période) | E4: Périodicité | F4: Montant mensuel | G4: Compte de réception | H4: Jour du mois
A5: Salaire Alex | B5: Salaire | C5: Alex | D5: 2400 | E5: Mensuelle | F5: =IF(A5="","",IFERROR(D5/INDEX(Paramètres!$E$4:$E$7,MATCH(E5,Paramètres!$D$4:$D$7,0)),0)) -> 2400 | G5: Compte Alex | H5: 28
A6: Salaire Sam | B6: Salaire | C6: Sam | D6: 1900 | E6: Mensuelle | F6: =IF(A6="","",IFERROR(D6/INDEX(Paramètres!$E$4:$E$7,MATCH(E6,Paramètres!$D$4:$D$7,0)),0)) -> 1900 | G6: Compte Sam | H6: 30
A7: Allocations familiales (CAF) | B7: Aide | C7: Commun | D7: 140 | E7: Mensuelle | F7: =IF(A7="","",IFERROR(D7/INDEX(Paramètres!$E$4:$E$7,MATCH(E7,Paramètres!$D$4:$D$7,0)),0)) -> 140 | G7: Joint Vie courante | H7: 5
A8: Prime d'activité (CAF) | B8: Aide | C8: Commun | D8: 270 | E8: Trimestrielle | F8: =IF(A8="","",IFERROR(D8/INDEX(Paramètres!$E$4:$E$7,MATCH(E8,Paramètres!$D$4:$D$7,0)),0)) -> 90 | G8: Joint Vie courante | H8: 5
F9: =IF(A9="","",IFERROR(D9/INDEX(Paramètres!$E$4:$E$7,MATCH(E9,Paramètres!$D$4:$D$7,0)),0))
F10: =IF(A10="","",IFERROR(D10/INDEX(Paramètres!$E$4:$E$7,MATCH(E10,Paramètres!$D$4:$D$7,0)),0))
F11: =IF(A11="","",IFERROR(D11/INDEX(Paramètres!$E$4:$E$7,MATCH(E11,Paramètres!$D$4:$D$7,0)),0))
F12: =IF(A12="","",IFERROR(D12/INDEX(Paramètres!$E$4:$E$7,MATCH(E12,Paramètres!$D$4:$D$7,0)),0))
F13: =IF(A13="","",IFERROR(D13/INDEX(Paramètres!$E$4:$E$7,MATCH(E13,Paramètres!$D$4:$D$7,0)),0))
F14: =IF(A14="","",IFERROR(D14/INDEX(Paramètres!$E$4:$E$7,MATCH(E14,Paramètres!$D$4:$D$7,0)),0))
F15: =IF(A15="","",IFERROR(D15/INDEX(Paramètres!$E$4:$E$7,MATCH(E15,Paramètres!$D$4:$D$7,0)),0))
F16: =IF(A16="","",IFERROR(D16/INDEX(Paramètres!$E$4:$E$7,MATCH(E16,Paramètres!$D$4:$D$7,0)),0))
F17: =IF(A17="","",IFERROR(D17/INDEX(Paramètres!$E$4:$E$7,MATCH(E17,Paramètres!$D$4:$D$7,0)),0))
F18: =IF(A18="","",IFERROR(D18/INDEX(Paramètres!$E$4:$E$7,MATCH(E18,Paramètres!$D$4:$D$7,0)),0))
F19: =IF(A19="","",IFERROR(D19/INDEX(Paramètres!$E$4:$E$7,MATCH(E19,Paramètres!$D$4:$D$7,0)),0))
F20: =IF(A20="","",IFERROR(D20/INDEX(Paramètres!$E$4:$E$7,MATCH(E20,Paramètres!$D$4:$D$7,0)),0))
... F24: =IF(A24="","",IFERROR(D24/INDEX(Paramètres!$E$4:$E$7,MATCH(E24,Paramètres!$D$4:$D$7,0)),0))
A25: TOTAL mensuel | F25: =SUM(F5:F24) -> 4530

Sheet Charges perso
A1: Charges personnelles (facultatif)
A2: Dépenses propres à chacun. Utilisé seulement si le mode « Détail » est choisi pour la personne dans Paramètres.
A4: Libellé | B4: Personne | C4: Catégorie | D4: Périodicité | E4: Montant (€ par période) | F4: Montant mensuel | G4: Mode de paiement | H4: Compte débité | I4: Jour du mois
A5: Salle de sport | B5: Alex | C5: Loisirs | D5: Mensuelle | E5: 35 | F5: =IF(A5="","",IFERROR(E5/INDEX(Paramètres!$E$4:$E$7,MATCH(D5,Paramètres!$D$4:$D$7,0)),0)) -> 35 | G5: Prélèvement | H5: Compte Alex | I5: 10
A6: Coiffeur | B6: Alex | C6: Soins | D6: Trimestrielle | E6: 120 | F6: =IF(A6="","",IFERROR(E6/INDEX(Paramètres!$E$4:$E$7,MATCH(D6,Paramètres!$D$4:$D$7,0)),0)) -> 40 | G6: Carte | H6: Compte Alex
A7: Abonnement musique | B7: Alex | C7: Abonnements | D7: Mensuelle | E7: 11 | F7: =IF(A7="","",IFERROR(E7/INDEX(Paramètres!$E$4:$E$7,MATCH(D7,Paramètres!$D$4:$D$7,0)),0)) -> 11 | G7: Prélèvement | H7: Compte Alex | I7: 15
F8: =IF(A8="","",IFERROR(E8/INDEX(Paramètres!$E$4:$E$7,MATCH(D8,Paramètres!$D$4:$D$7,0)),0))
F9: =IF(A9="","",IFERROR(E9/INDEX(Paramètres!$E$4:$E$7,MATCH(D9,Paramètres!$D$4:$D$7,0)),0))
F10: =IF(A10="","",IFERROR(E10/INDEX(Paramètres!$E$4:$E$7,MATCH(D10,Paramètres!$D$4:$D$7,0)),0))
F11: =IF(A11="","",IFERROR(E11/INDEX(Paramètres!$E$4:$E$7,MATCH(D11,Paramètres!$D$4:$D$7,0)),0))
F12: =IF(A12="","",IFERROR(E12/INDEX(Paramètres!$E$4:$E$7,MATCH(D12,Paramètres!$D$4:$D$7,0)),0))
F13: =IF(A13="","",IFERROR(E13/INDEX(Paramètres!$E$4:$E$7,MATCH(D13,Paramètres!$D$4:$D$7,0)),0))
F14: =IF(A14="","",IFERROR(E14/INDEX(Paramètres!$E$4:$E$7,MATCH(D14,Paramètres!$D$4:$D$7,0)),0))
F15: =IF(A15="","",IFERROR(E15/INDEX(Paramètres!$E$4:$E$7,MATCH(D15,Paramètres!$D$4:$D$7,0)),0))
F16: =IF(A16="","",IFERROR(E16/INDEX(Paramètres!$E$4:$E$7,MATCH(D16,Paramètres!$D$4:$D$7,0)),0))
F17: =IF(A17="","",IFERROR(E17/INDEX(Paramètres!$E$4:$E$7,MATCH(D17,Paramètres!$D$4:$D$7,0)),0))
F18: =IF(A18="","",IFERROR(E18/INDEX(Paramètres!$E$4:$E$7,MATCH(D18,Paramètres!$D$4:$D$7,0)),0))
F19: =IF(A19="","",IFERROR(E19/INDEX(Paramètres!$E$4:$E$7,MATCH(D19,Paramètres!$D$4:$D$7,0)),0))
... F44: =IF(A44="","",IFERROR(E44/INDEX(Paramètres!$E$4:$E$7,MATCH(D44,Paramètres!$D$4:$D$7,0)),0))
A45: TOTAL mensuel | F45: =SUM(F5:F44) -> 86

Sheet Imprévus
A1: Suivi des imprévus
A2: Notez chaque dépense imprévue ici (date, libellé, montant). Le solde de la provision se met à jour tout seul.
A4: Provision mensuelle (ligne « Imprévus » de Charges) | B4: =SUMIFS(Charges!$F$5:$F$54,Charges!$B$5:$B$54,"Imprévus") -> 129
A5: Début du suivi (1er du mois) | B5: 46266
A6: Solde de départ du livret imprévus | B6: 0
A7: Mois provisionnés (mois en cours inclus) | B7: =IF(B5="",0,MAX(0,(YEAR(TODAY())-YEAR(B5))*12+MONTH(TODAY())-MONTH(B5)+1)) -> 2
A8: Total provisionné | B8: =B6+B4*B7 -> 258
A9: Total dépensé en imprévus | B9: =SUM(C13:C62) -> 305
A10: Solde de la provision | B10: =B8-B9 -> -47
A11: Solde négatif = la provision n'a pas suffi : à combler avec l'épargne ou le reste libre.
A12: Date | B12: Libellé | C12: Montant (€) | D12: Payé depuis
A13: 46285 | B13: Pare-brise | C13: 220 | D13: Livret imprévus
A14: 46300 | B14: Dentiste | C14: 85 | D14: Livret imprévus
